docliteshared.so
pydoclite/__init__.py
pydoclite/doclite.py
pydoclite/docliteshared.so
pydoclite-0.1.0.dist-info/METADATA
pydoclite-0.1.0.dist-info/WHEEL
pydoclite-0.1.0.dist-info/top_level.txt
pydoclite-0.1.0.dist-info/RECORD
