Metadata-Version: 2.1
Name: pydoclite
Version: 0.1.0
Summary: pydoclite is the python library interface for doclite
Home-page: UNKNOWN
Author: abrahamakerele38@gmail.com
Author-email: UNKNOWN
License: MIT
Platform: UNKNOWN
